moffetthub-0.7.0.dist-info/licenses/LICENSE
moffetthub_cli/__init__.py
moffetthub_cli/i18n.py
moffetthub_cli/main.py
moffetthub_cli/utils.py
moffetthub-0.7.0.dist-info/METADATA
moffetthub-0.7.0.dist-info/WHEEL
moffetthub-0.7.0.dist-info/entry_points.txt
moffetthub-0.7.0.dist-info/top_level.txt
moffetthub-0.7.0.dist-info/RECORD
